<?xml version="1.0" encoding="utf-8"?>
<updates>
	<update>
	<name>French Translation of Flexicontent</name>
	<description>French Translation of Flexicontent</description>
	<element>pkg_fr-FR</element>
	<type>file</type>
	<version>3.3.1.4</version>
	<downloads>
	<downloadurl type="full" format="zip">
	https://crowdin.com/backend/download/project/flexicontent-cck-for-joomla/fr.zip
	</downloadurl>
	</downloads>
	<tags>
	<tag>stable</tag>
	</tags>
	<targetplatform name="joomla" version="3"/>
	</update>
</updates>